hyperion/__init__.py
hyperion/asyncutils.py
hyperion/catalog/__init__.py
hyperion/catalog/catalog.py
hyperion/catalog/schema.py
hyperion/config.py
hyperion/dateutils.py
hyperion/entities/__init__.py
hyperion/entities/catalog.py
hyperion/infrastructure/__init__.py
hyperion/infrastructure/aws.py
hyperion/infrastructure/cache.py
hyperion/infrastructure/geo/__init__.py
hyperion/infrastructure/geo/gmaps.py
hyperion/infrastructure/geo/location.py
hyperion/infrastructure/httputils.py
hyperion/infrastructure/keyval.py
hyperion/infrastructure/message_queue.py
hyperion/infrastructure/secretsmanager.py
hyperion/log.py
hyperion/py.typed
hyperion/repository/__init__.py
hyperion/repository/asset_collection.py
hyperion/sources/__init__.py
hyperion/sources/base.py
hyperion/sources/cli.py
hyperion/typeutils.py
hyperion_sdk-0.13.0.dist-info/METADATA
hyperion_sdk-0.13.0.dist-info/WHEEL
hyperion_sdk-0.13.0.dist-info/RECORD
