Metadata-Version: 2.4
Name: hyperion-sdk
Version: 0.13.0
Summary: A headless ETL / ELT / data pipeline and integration SDK for Python.
License: MIT
Author: Tomas Votava
Author-email: info@tomasvotava.eu
Requires-Python: >=3.10,<3.14
Classifier: License :: OSI Approved :: MIT License
Classifier: Programming Language :: Python :: 3
Classifier: Programming Language :: Python :: 3.10
Classifier: Programming Language :: Python :: 3.11
Classifier: Programming Language :: Python :: 3.12
Classifier: Programming Language :: Python :: 3.13
Requires-Dist: aioboto3 (>=13.2.0,<14.0.0)
Requires-Dist: aws-lambda-typing (>=2.20.0,<3.0.0)
Requires-Dist: boto3 (>=1.35.36,<2.0.0)
Requires-Dist: cachetools (>=5.5.2,<7.0.0)
Requires-Dist: click (>=8.2.1,<9.0.0)
Requires-Dist: env-proxy (>=1.1.1,<2.0.0)
Requires-Dist: fastavro (>=1.10.0,<2.0.0)
Requires-Dist: googlemaps (>=4.10.0,<5.0.0)
Requires-Dist: haversine (>=2.9.0,<3.0.0)
Requires-Dist: httpx (>=0.28.1,<0.29.0)
Requires-Dist: loguru (>=0.7.2,<0.8.0)
Requires-Dist: numpy (>=2.2.3,<3.0.0)
Requires-Dist: pandera[pandas,polars] (>=0.23.1,<0.27.0)
Requires-Dist: polars (>=1.26.0,<2.0.0)
Requires-Dist: pydantic (>=2.10.6,<3.0.0)
Requires-Dist: python-dateutil (>=2.9.0.post0,<3.0.0)
Requires-Dist: python-dotenv (>=1.0.1,<2.0.0)
Requires-Dist: python-snappy (>=0.7.3,<0.8.0)
